{
    "description": "",
    "tags": [],
    "size": {
        "height": 1920,
        "width": 1080
    },
    "objects": [
        {
            "id": 7681147,
            "classId": 22954,
            "description": "",
            "geometryType": "rectangle",
            "labelerLogin": "anna",
            "createdAt": "2021-02-12T09:50:48.352Z",
            "updatedAt": "2021-03-22T11:35:15.841Z",
            "tags": [],
            "classTitle": "product",
            "points": {
                "exterior": [
                    [
                        984,
                        0
                    ],
                    [
                        1074,
                        249
                    ]
                ],
                "interior": []
            }
        },
        {
            "id": 7681146,
            "classId": 22954,
            "description": "",
            "geometryType": "rectangle",
            "labelerLogin": "anna",
            "createdAt": "2021-02-12T09:50:52.796Z",
            "updatedAt": "2021-03-22T11:35:15.841Z",
            "tags": [],
            "classTitle": "product",
            "points": {
                "exterior": [
                    [
                        652,
                        0
                    ],
                    [
                        837,
                        274
                    ]
                ],
                "interior": []
            }
        },
        {
            "id": 7681145,
            "classId": 22954,
            "description": "",
            "geometryType": "rectangle",
            "labelerLogin": "anna",
            "createdAt": "2021-02-12T09:50:54.977Z",
            "updatedAt": "2021-03-22T11:35:15.841Z",
            "tags": [],
            "classTitle": "product",
            "points": {
                "exterior": [
                    [
                        468,
                        0
                    ],
                    [
                        645,
                        251
                    ]
                ],
                "interior": []
            }
        },
        {
            "id": 7681144,
            "classId": 22954,
            "description": "",
            "geometryType": "rectangle",
            "labelerLogin": "anna",
            "createdAt": "2021-02-12T09:50:57.144Z",
            "updatedAt": "2021-03-22T11:35:15.841Z",
            "tags": [],
            "classTitle": "product",
            "points": {
                "exterior": [
                    [
                        278,
                        0
                    ],
                    [
                        462,
                        273
                    ]
                ],
                "interior": []
            }
        },
        {
            "id": 7681143,
            "classId": 22954,
            "description": "",
            "geometryType": "rectangle",
            "labelerLogin": "anna",
            "createdAt": "2021-02-12T09:50:59.165Z",
            "updatedAt": "2021-03-22T11:35:15.841Z",
            "tags": [],
            "classTitle": "product",
            "points": {
                "exterior": [
                    [
                        72,
                        27
                    ],
                    [
                        264,
                        265
                    ]
                ],
                "interior": []
            }
        },
        {
            "id": 7681142,
            "classId": 22954,
            "description": "",
            "geometryType": "rectangle",
            "labelerLogin": "anna",
            "createdAt": "2021-02-12T09:51:01.310Z",
            "updatedAt": "2021-03-22T11:35:15.841Z",
            "tags": [],
            "classTitle": "product",
            "points": {
                "exterior": [
                    [
                        60,
                        430
                    ],
                    [
                        207,
                        671
                    ]
                ],
                "interior": []
            }
        },
        {
            "id": 7681141,
            "classId": 22954,
            "description": "",
            "geometryType": "rectangle",
            "labelerLogin": "anna",
            "createdAt": "2021-02-12T09:51:03.136Z",
            "updatedAt": "2021-03-22T11:35:15.841Z",
            "tags": [],
            "classTitle": "product",
            "points": {
                "exterior": [
                    [
                        188,
                        426
                    ],
                    [
                        349,
                        671
                    ]
                ],
                "interior": []
            }
        },
        {
            "id": 7681140,
            "classId": 22954,
            "description": "",
            "geometryType": "rectangle",
            "labelerLogin": "anna",
            "createdAt": "2021-02-12T09:51:05.405Z",
            "updatedAt": "2021-03-22T11:35:15.841Z",
            "tags": [],
            "classTitle": "product",
            "points": {
                "exterior": [
                    [
                        350,
                        405
                    ],
                    [
                        509,
                        659
                    ]
                ],
                "interior": []
            }
        },
        {
            "id": 7681139,
            "classId": 22954,
            "description": "",
            "geometryType": "rectangle",
            "labelerLogin": "anna",
            "createdAt": "2021-02-12T09:51:08.869Z",
            "updatedAt": "2021-03-22T11:35:15.841Z",
            "tags": [],
            "classTitle": "product",
            "points": {
                "exterior": [
                    [
                        505,
                        413
                    ],
                    [
                        635,
                        656
                    ]
                ],
                "interior": []
            }
        },
        {
            "id": 7681138,
            "classId": 22954,
            "description": "",
            "geometryType": "rectangle",
            "labelerLogin": "anna",
            "createdAt": "2021-02-12T09:51:10.765Z",
            "updatedAt": "2021-03-22T11:35:15.841Z",
            "tags": [],
            "classTitle": "product",
            "points": {
                "exterior": [
                    [
                        634,
                        434
                    ],
                    [
                        838,
                        654
                    ]
                ],
                "interior": []
            }
        },
        {
            "id": 7681137,
            "classId": 22954,
            "description": "",
            "geometryType": "rectangle",
            "labelerLogin": "anna",
            "createdAt": "2021-02-12T09:51:12.705Z",
            "updatedAt": "2021-03-22T11:35:15.841Z",
            "tags": [],
            "classTitle": "product",
            "points": {
                "exterior": [
                    [
                        830,
                        449
                    ],
                    [
                        947,
                        642
                    ]
                ],
                "interior": []
            }
        },
        {
            "id": 7681136,
            "classId": 22954,
            "description": "",
            "geometryType": "rectangle",
            "labelerLogin": "anna",
            "createdAt": "2021-02-12T09:51:14.414Z",
            "updatedAt": "2021-03-22T11:58:30.366Z",
            "tags": [],
            "classTitle": "product",
            "points": {
                "exterior": [
                    [
                        995,
                        409
                    ],
                    [
                        1068,
                        604
                    ]
                ],
                "interior": []
            }
        },
        {
            "id": 7681135,
            "classId": 22954,
            "description": "",
            "geometryType": "rectangle",
            "labelerLogin": "anna",
            "createdAt": "2021-02-12T09:51:18.077Z",
            "updatedAt": "2021-03-22T11:35:15.841Z",
            "tags": [],
            "classTitle": "product",
            "points": {
                "exterior": [
                    [
                        999,
                        777
                    ],
                    [
                        1079,
                        1007
                    ]
                ],
                "interior": []
            }
        },
        {
            "id": 7681134,
            "classId": 22954,
            "description": "",
            "geometryType": "rectangle",
            "labelerLogin": "anna",
            "createdAt": "2021-02-12T09:51:19.988Z",
            "updatedAt": "2021-03-22T11:35:15.841Z",
            "tags": [],
            "classTitle": "product",
            "points": {
                "exterior": [
                    [
                        760,
                        835
                    ],
                    [
                        916,
                        1012
                    ]
                ],
                "interior": []
            }
        },
        {
            "id": 7681133,
            "classId": 22954,
            "description": "",
            "geometryType": "rectangle",
            "labelerLogin": "anna",
            "createdAt": "2021-02-12T09:51:22.261Z",
            "updatedAt": "2021-03-22T11:35:15.841Z",
            "tags": [],
            "classTitle": "product",
            "points": {
                "exterior": [
                    [
                        634,
                        830
                    ],
                    [
                        796,
                        1038
                    ]
                ],
                "interior": []
            }
        },
        {
            "id": 7681132,
            "classId": 22954,
            "description": "",
            "geometryType": "rectangle",
            "labelerLogin": "anna",
            "createdAt": "2021-02-12T09:51:24.723Z",
            "updatedAt": "2021-03-22T11:35:15.841Z",
            "tags": [],
            "classTitle": "product",
            "points": {
                "exterior": [
                    [
                        511,
                        845
                    ],
                    [
                        650,
                        1051
                    ]
                ],
                "interior": []
            }
        },
        {
            "id": 7681131,
            "classId": 22954,
            "description": "",
            "geometryType": "rectangle",
            "labelerLogin": "anna",
            "createdAt": "2021-02-12T09:51:26.696Z",
            "updatedAt": "2021-03-22T11:35:15.841Z",
            "tags": [],
            "classTitle": "product",
            "points": {
                "exterior": [
                    [
                        388,
                        863
                    ],
                    [
                        528,
                        1028
                    ]
                ],
                "interior": []
            }
        },
        {
            "id": 7681130,
            "classId": 22954,
            "description": "",
            "geometryType": "rectangle",
            "labelerLogin": "anna",
            "createdAt": "2021-02-12T09:51:28.455Z",
            "updatedAt": "2021-03-22T11:35:15.841Z",
            "tags": [],
            "classTitle": "product",
            "points": {
                "exterior": [
                    [
                        288,
                        867
                    ],
                    [
                        425,
                        1038
                    ]
                ],
                "interior": []
            }
        },
        {
            "id": 7681129,
            "classId": 22954,
            "description": "",
            "geometryType": "rectangle",
            "labelerLogin": "anna",
            "createdAt": "2021-02-12T09:51:30.040Z",
            "updatedAt": "2021-03-22T11:35:15.841Z",
            "tags": [],
            "classTitle": "product",
            "points": {
                "exterior": [
                    [
                        127,
                        888
                    ],
                    [
                        297,
                        1065
                    ]
                ],
                "interior": []
            }
        },
        {
            "id": 7681128,
            "classId": 22954,
            "description": "",
            "geometryType": "rectangle",
            "labelerLogin": "anna",
            "createdAt": "2021-02-12T09:51:33.580Z",
            "updatedAt": "2021-03-22T11:35:15.841Z",
            "tags": [],
            "classTitle": "product",
            "points": {
                "exterior": [
                    [
                        928,
                        1127
                    ],
                    [
                        1060,
                        1313
                    ]
                ],
                "interior": []
            }
        },
        {
            "id": 7681127,
            "classId": 22954,
            "description": "",
            "geometryType": "rectangle",
            "labelerLogin": "anna",
            "createdAt": "2021-02-12T09:51:35.620Z",
            "updatedAt": "2021-03-22T11:35:15.841Z",
            "tags": [],
            "classTitle": "product",
            "points": {
                "exterior": [
                    [
                        786,
                        1166
                    ],
                    [
                        883,
                        1306
                    ]
                ],
                "interior": []
            }
        },
        {
            "id": 7681126,
            "classId": 22954,
            "description": "",
            "geometryType": "rectangle",
            "labelerLogin": "anna",
            "createdAt": "2021-02-12T09:51:37.256Z",
            "updatedAt": "2021-03-22T11:35:15.841Z",
            "tags": [],
            "classTitle": "product",
            "points": {
                "exterior": [
                    [
                        660,
                        1162
                    ],
                    [
                        802,
                        1327
                    ]
                ],
                "interior": []
            }
        },
        {
            "id": 7681125,
            "classId": 22954,
            "description": "",
            "geometryType": "rectangle",
            "labelerLogin": "anna",
            "createdAt": "2021-02-12T09:51:39.195Z",
            "updatedAt": "2021-03-22T11:35:15.841Z",
            "tags": [],
            "classTitle": "product",
            "points": {
                "exterior": [
                    [
                        554,
                        1230
                    ],
                    [
                        662,
                        1323
                    ]
                ],
                "interior": []
            }
        },
        {
            "id": 7681124,
            "classId": 22954,
            "description": "",
            "geometryType": "rectangle",
            "labelerLogin": "anna",
            "createdAt": "2021-02-12T09:51:42.681Z",
            "updatedAt": "2021-03-22T11:35:15.841Z",
            "tags": [],
            "classTitle": "product",
            "points": {
                "exterior": [
                    [
                        436,
                        1169
                    ],
                    [
                        560,
                        1328
                    ]
                ],
                "interior": []
            }
        },
        {
            "id": 7681123,
            "classId": 22954,
            "description": "",
            "geometryType": "rectangle",
            "labelerLogin": "anna",
            "createdAt": "2021-02-12T09:51:44.730Z",
            "updatedAt": "2021-03-22T11:35:15.841Z",
            "tags": [],
            "classTitle": "product",
            "points": {
                "exterior": [
                    [
                        285,
                        1153
                    ],
                    [
                        424,
                        1348
                    ]
                ],
                "interior": []
            }
        },
        {
            "id": 7681122,
            "classId": 22954,
            "description": "",
            "geometryType": "rectangle",
            "labelerLogin": "anna",
            "createdAt": "2021-02-12T09:51:46.832Z",
            "updatedAt": "2021-03-22T11:35:15.841Z",
            "tags": [],
            "classTitle": "product",
            "points": {
                "exterior": [
                    [
                        164,
                        1179
                    ],
                    [
                        316,
                        1362
                    ]
                ],
                "interior": []
            }
        },
        {
            "id": 7681121,
            "classId": 22954,
            "description": "",
            "geometryType": "rectangle",
            "labelerLogin": "anna",
            "createdAt": "2021-02-12T09:51:48.862Z",
            "updatedAt": "2021-03-22T11:35:15.841Z",
            "tags": [],
            "classTitle": "product",
            "points": {
                "exterior": [
                    [
                        0,
                        1189
                    ],
                    [
                        126,
                        1381
                    ]
                ],
                "interior": []
            }
        },
        {
            "id": 7681120,
            "classId": 22954,
            "description": "",
            "geometryType": "rectangle",
            "labelerLogin": "anna",
            "createdAt": "2021-02-12T09:51:51.309Z",
            "updatedAt": "2021-03-22T11:35:15.841Z",
            "tags": [],
            "classTitle": "product",
            "points": {
                "exterior": [
                    [
                        7,
                        1432
                    ],
                    [
                        137,
                        1585
                    ]
                ],
                "interior": []
            }
        },
        {
            "id": 7681119,
            "classId": 22954,
            "description": "",
            "geometryType": "rectangle",
            "labelerLogin": "anna",
            "createdAt": "2021-02-12T09:51:53.240Z",
            "updatedAt": "2021-03-22T11:35:15.841Z",
            "tags": [],
            "classTitle": "product",
            "points": {
                "exterior": [
                    [
                        13,
                        1544
                    ],
                    [
                        144,
                        1679
                    ]
                ],
                "interior": []
            }
        },
        {
            "id": 7681118,
            "classId": 22954,
            "description": "",
            "geometryType": "rectangle",
            "labelerLogin": "anna",
            "createdAt": "2021-02-12T09:51:55.257Z",
            "updatedAt": "2021-03-22T11:35:15.841Z",
            "tags": [],
            "classTitle": "product",
            "points": {
                "exterior": [
                    [
                        233,
                        1418
                    ],
                    [
                        307,
                        1533
                    ]
                ],
                "interior": []
            }
        },
        {
            "id": 7681117,
            "classId": 22954,
            "description": "",
            "geometryType": "rectangle",
            "labelerLogin": "anna",
            "createdAt": "2021-02-12T09:51:57.043Z",
            "updatedAt": "2021-03-22T11:35:15.841Z",
            "tags": [],
            "classTitle": "product",
            "points": {
                "exterior": [
                    [
                        307,
                        1504
                    ],
                    [
                        390,
                        1583
                    ]
                ],
                "interior": []
            }
        },
        {
            "id": 7681116,
            "classId": 22954,
            "description": "",
            "geometryType": "rectangle",
            "labelerLogin": "anna",
            "createdAt": "2021-02-12T09:51:59.163Z",
            "updatedAt": "2021-03-22T11:35:15.841Z",
            "tags": [],
            "classTitle": "product",
            "points": {
                "exterior": [
                    [
                        368,
                        1397
                    ],
                    [
                        460,
                        1521
                    ]
                ],
                "interior": []
            }
        },
        {
            "id": 7681115,
            "classId": 22954,
            "description": "",
            "geometryType": "rectangle",
            "labelerLogin": "anna",
            "createdAt": "2021-02-12T09:52:04.550Z",
            "updatedAt": "2021-03-22T11:35:15.841Z",
            "tags": [],
            "classTitle": "product",
            "points": {
                "exterior": [
                    [
                        639,
                        1403
                    ],
                    [
                        728,
                        1525
                    ]
                ],
                "interior": []
            }
        },
        {
            "id": 7681114,
            "classId": 22954,
            "description": "",
            "geometryType": "rectangle",
            "labelerLogin": "anna",
            "createdAt": "2021-02-12T09:52:06.440Z",
            "updatedAt": "2021-03-22T11:35:15.841Z",
            "tags": [],
            "classTitle": "product",
            "points": {
                "exterior": [
                    [
                        720,
                        1381
                    ],
                    [
                        794,
                        1504
                    ]
                ],
                "interior": []
            }
        },
        {
            "id": 7681113,
            "classId": 22954,
            "description": "",
            "geometryType": "rectangle",
            "labelerLogin": "anna",
            "createdAt": "2021-02-12T09:52:09.901Z",
            "updatedAt": "2021-03-22T11:35:15.841Z",
            "tags": [],
            "classTitle": "product",
            "points": {
                "exterior": [
                    [
                        916,
                        1339
                    ],
                    [
                        1079,
                        1593
                    ]
                ],
                "interior": []
            }
        }
    ]
}